{
  "actual_root_sha256": "21e5311d01d3838d49bcb775cfdaed3482f110915f6339f875b1206126318745",
  "claim_boundary": "Internal CI replay is not the same as independent reviewer replication. This artifact does not claim achieved AGI, ASI, empirical SOTA, safe autonomy, standard-setting control, guaranteed economic return, or civilization-scale capability. It records a bounded Evidence Docket. Stronger claims require independent replay, full baselines, cost/safety ledger review, delayed outcomes, and independent audit.",
  "expected_root_sha256": "490cc51c84767cc7d0405c2f10189f758b475f0add49e3c57a0e96ffb52ed063",
  "generated_at_epoch": 1777592978,
  "independent": false,
  "mismatches": [
    {
      "error": "json mismatch",
      "file": "00_manifest.json"
    }
  ],
  "schema": "agialpha.replay_report.v1",
  "status": "fail"
}
