{
  "shadow_control": [
    {
      "capability_hash": "not_used",
      "constraints": {
        "autonomous_persistence_allowed": false,
        "budget_units": 100,
        "claim_boundary": "local bounded public evidence; proof-gated recursive experiment engine; human-reviewed promotion required",
        "deterministic_seed": 1337,
        "execution_scope": "local_only",
        "external_targets_allowed": false,
        "human_review_required": true,
        "network_allowed": false,
        "no_auto_merge": true,
        "production_actuation_allowed": false,
        "regulated_boundary": "regulated-domain firewall enabled; blocked_human_review_required for regulated tasks",
        "safe_filesystem_root": "/workspace/agialpha-first-real-loop",
        "token_boundary": "$AGIALPHA utility-only accounting; no wallet/custody/payment/KYC/AML/trading"
      },
      "correct": true,
      "expected_valid": true,
      "fixture_id": "pb-heldout-complete",
      "mode": "shadow_control",
      "pair_id": "proofbundle_validator_pair",
      "predicted_valid": true,
      "score": 1.0,
      "used_frozen_capability": false
    },
    {
      "capability_hash": "not_used",
      "constraints": {
        "autonomous_persistence_allowed": false,
        "budget_units": 100,
        "claim_boundary": "local bounded public evidence; proof-gated recursive experiment engine; human-reviewed promotion required",
        "deterministic_seed": 1337,
        "execution_scope": "local_only",
        "external_targets_allowed": false,
        "human_review_required": true,
        "network_allowed": false,
        "no_auto_merge": true,
        "production_actuation_allowed": false,
        "regulated_boundary": "regulated-domain firewall enabled; blocked_human_review_required for regulated tasks",
        "safe_filesystem_root": "/workspace/agialpha-first-real-loop",
        "token_boundary": "$AGIALPHA utility-only accounting; no wallet/custody/payment/KYC/AML/trading"
      },
      "correct": false,
      "expected_valid": false,
      "fixture_id": "pb-heldout-no-capability",
      "mode": "shadow_control",
      "pair_id": "proofbundle_validator_pair",
      "predicted_valid": true,
      "score": 0.0,
      "used_frozen_capability": false
    },
    {
      "capability_hash": "not_used",
      "constraints": {
        "autonomous_persistence_allowed": false,
        "budget_units": 100,
        "claim_boundary": "local bounded public evidence; proof-gated recursive experiment engine; human-reviewed promotion required",
        "deterministic_seed": 1337,
        "execution_scope": "local_only",
        "external_targets_allowed": false,
        "human_review_required": true,
        "network_allowed": false,
        "no_auto_merge": true,
        "production_actuation_allowed": false,
        "regulated_boundary": "regulated-domain firewall enabled; blocked_human_review_required for regulated tasks",
        "safe_filesystem_root": "/workspace/agialpha-first-real-loop",
        "token_boundary": "$AGIALPHA utility-only accounting; no wallet/custody/payment/KYC/AML/trading"
      },
      "correct": false,
      "expected_valid": false,
      "fixture_id": "pb-heldout-no-fixture",
      "mode": "shadow_control",
      "pair_id": "proofbundle_validator_pair",
      "predicted_valid": true,
      "score": 0.0,
      "used_frozen_capability": false
    },
    {
      "capability_hash": "not_used",
      "constraints": {
        "autonomous_persistence_allowed": false,
        "budget_units": 100,
        "claim_boundary": "local bounded public evidence; proof-gated recursive experiment engine; human-reviewed promotion required",
        "deterministic_seed": 1337,
        "execution_scope": "local_only",
        "external_targets_allowed": false,
        "human_review_required": true,
        "network_allowed": false,
        "no_auto_merge": true,
        "production_actuation_allowed": false,
        "regulated_boundary": "regulated-domain firewall enabled; blocked_human_review_required for regulated tasks",
        "safe_filesystem_root": "/workspace/agialpha-first-real-loop",
        "token_boundary": "$AGIALPHA utility-only accounting; no wallet/custody/payment/KYC/AML/trading"
      },
      "correct": false,
      "expected_valid": true,
      "fixture_id": "claim-heldout-safe",
      "mode": "shadow_control",
      "pair_id": "claim_boundary_validator_pair",
      "predicted_valid": false,
      "score": 0.0,
      "used_frozen_capability": false
    },
    {
      "capability_hash": "not_used",
      "constraints": {
        "autonomous_persistence_allowed": false,
        "budget_units": 100,
        "claim_boundary": "local bounded public evidence; proof-gated recursive experiment engine; human-reviewed promotion required",
        "deterministic_seed": 1337,
        "execution_scope": "local_only",
        "external_targets_allowed": false,
        "human_review_required": true,
        "network_allowed": false,
        "no_auto_merge": true,
        "production_actuation_allowed": false,
        "regulated_boundary": "regulated-domain firewall enabled; blocked_human_review_required for regulated tasks",
        "safe_filesystem_root": "/workspace/agialpha-first-real-loop",
        "token_boundary": "$AGIALPHA utility-only accounting; no wallet/custody/payment/KYC/AML/trading"
      },
      "correct": false,
      "expected_valid": false,
      "fixture_id": "claim-heldout-sota",
      "mode": "shadow_control",
      "pair_id": "claim_boundary_validator_pair",
      "predicted_valid": true,
      "score": 0.0,
      "used_frozen_capability": false
    },
    {
      "capability_hash": "not_used",
      "constraints": {
        "autonomous_persistence_allowed": false,
        "budget_units": 100,
        "claim_boundary": "local bounded public evidence; proof-gated recursive experiment engine; human-reviewed promotion required",
        "deterministic_seed": 1337,
        "execution_scope": "local_only",
        "external_targets_allowed": false,
        "human_review_required": true,
        "network_allowed": false,
        "no_auto_merge": true,
        "production_actuation_allowed": false,
        "regulated_boundary": "regulated-domain firewall enabled; blocked_human_review_required for regulated tasks",
        "safe_filesystem_root": "/workspace/agialpha-first-real-loop",
        "token_boundary": "$AGIALPHA utility-only accounting; no wallet/custody/payment/KYC/AML/trading"
      },
      "correct": false,
      "expected_valid": false,
      "fixture_id": "claim-heldout-asi",
      "mode": "shadow_control",
      "pair_id": "claim_boundary_validator_pair",
      "predicted_valid": true,
      "score": 0.0,
      "used_frozen_capability": false
    },
    {
      "capability_hash": "not_used",
      "constraints": {
        "autonomous_persistence_allowed": false,
        "budget_units": 100,
        "claim_boundary": "local bounded public evidence; proof-gated recursive experiment engine; human-reviewed promotion required",
        "deterministic_seed": 1337,
        "execution_scope": "local_only",
        "external_targets_allowed": false,
        "human_review_required": true,
        "network_allowed": false,
        "no_auto_merge": true,
        "production_actuation_allowed": false,
        "regulated_boundary": "regulated-domain firewall enabled; blocked_human_review_required for regulated tasks",
        "safe_filesystem_root": "/workspace/agialpha-first-real-loop",
        "token_boundary": "$AGIALPHA utility-only accounting; no wallet/custody/payment/KYC/AML/trading"
      },
      "correct": true,
      "expected_valid": true,
      "fixture_id": "workflow-heldout-safe",
      "mode": "shadow_control",
      "pair_id": "workflow_catalog_repair_pair",
      "predicted_valid": true,
      "score": 1.0,
      "used_frozen_capability": false
    },
    {
      "capability_hash": "not_used",
      "constraints": {
        "autonomous_persistence_allowed": false,
        "budget_units": 100,
        "claim_boundary": "local bounded public evidence; proof-gated recursive experiment engine; human-reviewed promotion required",
        "deterministic_seed": 1337,
        "execution_scope": "local_only",
        "external_targets_allowed": false,
        "human_review_required": true,
        "network_allowed": false,
        "no_auto_merge": true,
        "production_actuation_allowed": false,
        "regulated_boundary": "regulated-domain firewall enabled; blocked_human_review_required for regulated tasks",
        "safe_filesystem_root": "/workspace/agialpha-first-real-loop",
        "token_boundary": "$AGIALPHA utility-only accounting; no wallet/custody/payment/KYC/AML/trading"
      },
      "correct": false,
      "expected_valid": false,
      "fixture_id": "workflow-heldout-pages",
      "mode": "shadow_control",
      "pair_id": "workflow_catalog_repair_pair",
      "predicted_valid": true,
      "score": 0.0,
      "used_frozen_capability": false
    },
    {
      "capability_hash": "not_used",
      "constraints": {
        "autonomous_persistence_allowed": false,
        "budget_units": 100,
        "claim_boundary": "local bounded public evidence; proof-gated recursive experiment engine; human-reviewed promotion required",
        "deterministic_seed": 1337,
        "execution_scope": "local_only",
        "external_targets_allowed": false,
        "human_review_required": true,
        "network_allowed": false,
        "no_auto_merge": true,
        "production_actuation_allowed": false,
        "regulated_boundary": "regulated-domain firewall enabled; blocked_human_review_required for regulated tasks",
        "safe_filesystem_root": "/workspace/agialpha-first-real-loop",
        "token_boundary": "$AGIALPHA utility-only accounting; no wallet/custody/payment/KYC/AML/trading"
      },
      "correct": true,
      "expected_valid": false,
      "fixture_id": "workflow-heldout-merge",
      "mode": "shadow_control",
      "pair_id": "workflow_catalog_repair_pair",
      "predicted_valid": false,
      "score": 1.0,
      "used_frozen_capability": false
    }
  ],
  "treatment": [
    {
      "capability_hash": "fdecc3e42e6a4d0689f76757ed510bb84baa41faec7a83dc954946eaa57c9f84",
      "constraints": {
        "autonomous_persistence_allowed": false,
        "budget_units": 100,
        "claim_boundary": "local bounded public evidence; proof-gated recursive experiment engine; human-reviewed promotion required",
        "deterministic_seed": 1337,
        "execution_scope": "local_only",
        "external_targets_allowed": false,
        "human_review_required": true,
        "network_allowed": false,
        "no_auto_merge": true,
        "production_actuation_allowed": false,
        "regulated_boundary": "regulated-domain firewall enabled; blocked_human_review_required for regulated tasks",
        "safe_filesystem_root": "/workspace/agialpha-first-real-loop",
        "token_boundary": "$AGIALPHA utility-only accounting; no wallet/custody/payment/KYC/AML/trading"
      },
      "correct": true,
      "expected_valid": true,
      "fixture_id": "pb-heldout-complete",
      "mode": "treatment",
      "pair_id": "proofbundle_validator_pair",
      "predicted_valid": true,
      "score": 1.0,
      "used_frozen_capability": true
    },
    {
      "capability_hash": "fdecc3e42e6a4d0689f76757ed510bb84baa41faec7a83dc954946eaa57c9f84",
      "constraints": {
        "autonomous_persistence_allowed": false,
        "budget_units": 100,
        "claim_boundary": "local bounded public evidence; proof-gated recursive experiment engine; human-reviewed promotion required",
        "deterministic_seed": 1337,
        "execution_scope": "local_only",
        "external_targets_allowed": false,
        "human_review_required": true,
        "network_allowed": false,
        "no_auto_merge": true,
        "production_actuation_allowed": false,
        "regulated_boundary": "regulated-domain firewall enabled; blocked_human_review_required for regulated tasks",
        "safe_filesystem_root": "/workspace/agialpha-first-real-loop",
        "token_boundary": "$AGIALPHA utility-only accounting; no wallet/custody/payment/KYC/AML/trading"
      },
      "correct": true,
      "expected_valid": false,
      "fixture_id": "pb-heldout-no-capability",
      "mode": "treatment",
      "pair_id": "proofbundle_validator_pair",
      "predicted_valid": false,
      "score": 1.0,
      "used_frozen_capability": true
    },
    {
      "capability_hash": "fdecc3e42e6a4d0689f76757ed510bb84baa41faec7a83dc954946eaa57c9f84",
      "constraints": {
        "autonomous_persistence_allowed": false,
        "budget_units": 100,
        "claim_boundary": "local bounded public evidence; proof-gated recursive experiment engine; human-reviewed promotion required",
        "deterministic_seed": 1337,
        "execution_scope": "local_only",
        "external_targets_allowed": false,
        "human_review_required": true,
        "network_allowed": false,
        "no_auto_merge": true,
        "production_actuation_allowed": false,
        "regulated_boundary": "regulated-domain firewall enabled; blocked_human_review_required for regulated tasks",
        "safe_filesystem_root": "/workspace/agialpha-first-real-loop",
        "token_boundary": "$AGIALPHA utility-only accounting; no wallet/custody/payment/KYC/AML/trading"
      },
      "correct": true,
      "expected_valid": false,
      "fixture_id": "pb-heldout-no-fixture",
      "mode": "treatment",
      "pair_id": "proofbundle_validator_pair",
      "predicted_valid": false,
      "score": 1.0,
      "used_frozen_capability": true
    },
    {
      "capability_hash": "56e41ad8c476d6491cc79591da6577eb6ab99915a969c9479bd46b44127b46f1",
      "constraints": {
        "autonomous_persistence_allowed": false,
        "budget_units": 100,
        "claim_boundary": "local bounded public evidence; proof-gated recursive experiment engine; human-reviewed promotion required",
        "deterministic_seed": 1337,
        "execution_scope": "local_only",
        "external_targets_allowed": false,
        "human_review_required": true,
        "network_allowed": false,
        "no_auto_merge": true,
        "production_actuation_allowed": false,
        "regulated_boundary": "regulated-domain firewall enabled; blocked_human_review_required for regulated tasks",
        "safe_filesystem_root": "/workspace/agialpha-first-real-loop",
        "token_boundary": "$AGIALPHA utility-only accounting; no wallet/custody/payment/KYC/AML/trading"
      },
      "correct": true,
      "expected_valid": true,
      "fixture_id": "claim-heldout-safe",
      "mode": "treatment",
      "pair_id": "claim_boundary_validator_pair",
      "predicted_valid": true,
      "score": 1.0,
      "used_frozen_capability": true
    },
    {
      "capability_hash": "56e41ad8c476d6491cc79591da6577eb6ab99915a969c9479bd46b44127b46f1",
      "constraints": {
        "autonomous_persistence_allowed": false,
        "budget_units": 100,
        "claim_boundary": "local bounded public evidence; proof-gated recursive experiment engine; human-reviewed promotion required",
        "deterministic_seed": 1337,
        "execution_scope": "local_only",
        "external_targets_allowed": false,
        "human_review_required": true,
        "network_allowed": false,
        "no_auto_merge": true,
        "production_actuation_allowed": false,
        "regulated_boundary": "regulated-domain firewall enabled; blocked_human_review_required for regulated tasks",
        "safe_filesystem_root": "/workspace/agialpha-first-real-loop",
        "token_boundary": "$AGIALPHA utility-only accounting; no wallet/custody/payment/KYC/AML/trading"
      },
      "correct": true,
      "expected_valid": false,
      "fixture_id": "claim-heldout-sota",
      "mode": "treatment",
      "pair_id": "claim_boundary_validator_pair",
      "predicted_valid": false,
      "score": 1.0,
      "used_frozen_capability": true
    },
    {
      "capability_hash": "56e41ad8c476d6491cc79591da6577eb6ab99915a969c9479bd46b44127b46f1",
      "constraints": {
        "autonomous_persistence_allowed": false,
        "budget_units": 100,
        "claim_boundary": "local bounded public evidence; proof-gated recursive experiment engine; human-reviewed promotion required",
        "deterministic_seed": 1337,
        "execution_scope": "local_only",
        "external_targets_allowed": false,
        "human_review_required": true,
        "network_allowed": false,
        "no_auto_merge": true,
        "production_actuation_allowed": false,
        "regulated_boundary": "regulated-domain firewall enabled; blocked_human_review_required for regulated tasks",
        "safe_filesystem_root": "/workspace/agialpha-first-real-loop",
        "token_boundary": "$AGIALPHA utility-only accounting; no wallet/custody/payment/KYC/AML/trading"
      },
      "correct": true,
      "expected_valid": false,
      "fixture_id": "claim-heldout-asi",
      "mode": "treatment",
      "pair_id": "claim_boundary_validator_pair",
      "predicted_valid": false,
      "score": 1.0,
      "used_frozen_capability": true
    },
    {
      "capability_hash": "1d0328f633e90f6d2ae4181acf61369b41d196818da55b43d30a217f4a3cf882",
      "constraints": {
        "autonomous_persistence_allowed": false,
        "budget_units": 100,
        "claim_boundary": "local bounded public evidence; proof-gated recursive experiment engine; human-reviewed promotion required",
        "deterministic_seed": 1337,
        "execution_scope": "local_only",
        "external_targets_allowed": false,
        "human_review_required": true,
        "network_allowed": false,
        "no_auto_merge": true,
        "production_actuation_allowed": false,
        "regulated_boundary": "regulated-domain firewall enabled; blocked_human_review_required for regulated tasks",
        "safe_filesystem_root": "/workspace/agialpha-first-real-loop",
        "token_boundary": "$AGIALPHA utility-only accounting; no wallet/custody/payment/KYC/AML/trading"
      },
      "correct": true,
      "expected_valid": true,
      "fixture_id": "workflow-heldout-safe",
      "mode": "treatment",
      "pair_id": "workflow_catalog_repair_pair",
      "predicted_valid": true,
      "score": 1.0,
      "used_frozen_capability": true
    },
    {
      "capability_hash": "1d0328f633e90f6d2ae4181acf61369b41d196818da55b43d30a217f4a3cf882",
      "constraints": {
        "autonomous_persistence_allowed": false,
        "budget_units": 100,
        "claim_boundary": "local bounded public evidence; proof-gated recursive experiment engine; human-reviewed promotion required",
        "deterministic_seed": 1337,
        "execution_scope": "local_only",
        "external_targets_allowed": false,
        "human_review_required": true,
        "network_allowed": false,
        "no_auto_merge": true,
        "production_actuation_allowed": false,
        "regulated_boundary": "regulated-domain firewall enabled; blocked_human_review_required for regulated tasks",
        "safe_filesystem_root": "/workspace/agialpha-first-real-loop",
        "token_boundary": "$AGIALPHA utility-only accounting; no wallet/custody/payment/KYC/AML/trading"
      },
      "correct": true,
      "expected_valid": false,
      "fixture_id": "workflow-heldout-pages",
      "mode": "treatment",
      "pair_id": "workflow_catalog_repair_pair",
      "predicted_valid": false,
      "score": 1.0,
      "used_frozen_capability": true
    },
    {
      "capability_hash": "1d0328f633e90f6d2ae4181acf61369b41d196818da55b43d30a217f4a3cf882",
      "constraints": {
        "autonomous_persistence_allowed": false,
        "budget_units": 100,
        "claim_boundary": "local bounded public evidence; proof-gated recursive experiment engine; human-reviewed promotion required",
        "deterministic_seed": 1337,
        "execution_scope": "local_only",
        "external_targets_allowed": false,
        "human_review_required": true,
        "network_allowed": false,
        "no_auto_merge": true,
        "production_actuation_allowed": false,
        "regulated_boundary": "regulated-domain firewall enabled; blocked_human_review_required for regulated tasks",
        "safe_filesystem_root": "/workspace/agialpha-first-real-loop",
        "token_boundary": "$AGIALPHA utility-only accounting; no wallet/custody/payment/KYC/AML/trading"
      },
      "correct": true,
      "expected_valid": false,
      "fixture_id": "workflow-heldout-merge",
      "mode": "treatment",
      "pair_id": "workflow_catalog_repair_pair",
      "predicted_valid": false,
      "score": 1.0,
      "used_frozen_capability": true
    }
  ]
}
